{
  "responseCode": 200,
  "responseMessage": "Channel Detail",
  "response": {
    "id": 95,
    "title": "TV1",
    "description": "TV1 is a Malaysian free-to-air television channel airing various types of programmes, drama and news. Find out more on CH101 now!",
    "isHd": false,
    "stbNumber": "101",
    "language": "Multiple Language",
    "category": "Variety Entertainment",
    "originalImage": "http://linear-poster.astro.com.my/prod/logo/TV1_v1.png",
    "backupImage": "http://linear-poster.astro.com.my/prod/poster/ivp_default_1028_IVP_LAND_448x252.jpg",
    "imageUrl": "https://divign0fdw3sv.cloudfront.net/Images/ChannelLogo/contenthub/95_144.png",
    "isAstroGoExclusive": false,
    "filters": ["Set Top Box", "NJOI", "Variety Entertainment"],
    "schedule": {
      "2021-01-28": [
        {
          "eventId": "35977327",
          "title": "Berita Tengah Malam",
          "programmeId": null,
          "episodeId": null,
          "datetime": "2021-01-28 00:00:00.0",
          "datetimeInUtc": "2021-01-27 16:00:00.0",
          "duration": "00:30:00",
          "siTrafficKey": "1:1028:42612258",
          "detailUrl": "/details/Berita-Tengah-Malam-1:1028:42612258"
        },
        {
          "eventId": "36165444",
          "title": "Trans World Sports",
          "programmeId": null,
          "episodeId": null,
          "datetime": "2021-01-28 00:30:00.0",
          "datetimeInUtc": "2021-01-27 16:30:00.0",
          "duration": "01:00:00",
          "siTrafficKey": "1:1028:42903869",
          "detailUrl": "/details/Trans-World-Sports-1:1028:42903869"
        },
        {
          "eventId": "36165445",
          "title": "Sukan Lejen - Diskusi Imbasan",
          "programmeId": null,
          "episodeId": null,
          "datetime": "2021-01-28 01:30:00.0",
          "datetimeInUtc": "2021-01-27 17:30:00.0",
          "duration": "01:00:00",
          "siTrafficKey": "1:1028:42903870",
          "detailUrl": "/details/Sukan-Lejen-Diskusi-Imbasan-1:1028:42903870"
        },
        {
          "eventId": "35977331",
          "title": "Skuad Chenta",
          "programmeId": null,
          "episodeId": null,
          "datetime": "2021-01-28 02:30:00.0",
          "datetimeInUtc": "2021-01-27 18:30:00.0",
          "duration": "00:30:00",
          "siTrafficKey": "1:1028:42612262",
          "detailUrl": "/details/Skuad-Chenta-1:1028:42612262"
        },
        {
          "eventId": "36165446",
          "title": "Gelak Sampai Kenyang",
          "programmeId": null,
          "episodeId": null,
          "datetime": "2021-01-28 03:00:00.0",
          "datetimeInUtc": "2021-01-27 19:00:00.0",
          "duration": "00:30:00",
          "siTrafficKey": "1:1028:42903871",
          "detailUrl": "/details/Gelak-Sampai-Kenyang-1:1028:42903871"
        },
        {
          "eventId": "36165447",
          "title": "Dari Mata Arisa",
          "programmeId": null,
          "episodeId": null,
          "datetime": "2021-01-28 03:30:00.0",
          "datetimeInUtc": "2021-01-27 19:30:00.0",
          "duration": "01:00:00",
          "siTrafficKey": "1:1028:42903872",
          "detailUrl": "/details/Dari-Mata-Arisa-1:1028:42903872"
        },
        {
          "eventId": "36165448",
          "title": "Sinei Kitak Tok",
          "programmeId": null,
          "episodeId": null,
          "datetime": "2021-01-28 04:30:00.0",
          "datetimeInUtc": "2021-01-27 20:30:00.0",
          "duration": "00:30:00",
          "siTrafficKey": "1:1028:42903873",
          "detailUrl": "/details/Sinei-Kitak-Tok-1:1028:42903873"
        },
        {
          "eventId": "36165449",
          "title": "Mahligai Kaca",
          "programmeId": null,
          "episodeId": null,
          "datetime": "2021-01-28 05:00:00.0",
          "datetimeInUtc": "2021-01-27 21:00:00.0",
          "duration": "01:00:00",
          "siTrafficKey": "1:1028:42903874",
          "detailUrl": "/details/Mahligai-Kaca-1:1028:42903874"
        },
        {
          "eventId": "36165450",
          "title": "My Halal",
          "programmeId": null,
          "episodeId": null,
          "datetime": "2021-01-28 06:00:00.0",
          "datetimeInUtc": "2021-01-27 22:00:00.0",
          "duration": "01:00:00",
          "siTrafficKey": "1:1028:42903875",
          "detailUrl": "/details/My-Halal-1:1028:42903875"
        },
        {
          "eventId": "35990803",
          "title": "Berita Pagi",
          "programmeId": null,
          "episodeId": null,
          "datetime": "2021-01-28 07:00:00.0",
          "datetimeInUtc": "2021-01-27 23:00:00.0",
          "duration": "00:30:00",
          "siTrafficKey": "1:1028:42612268",
          "detailUrl": "/details/Berita-Pagi-1:1028:42612268"
        },
        {
          "eventId": "35990804",
          "title": "Berita Pagi Sabah",
          "programmeId": null,
          "episodeId": null,
          "datetime": "2021-01-28 07:30:00.0",
          "datetimeInUtc": "2021-01-27 23:30:00.0",
          "duration": "00:15:00",
          "siTrafficKey": "1:1028:42612269",
          "detailUrl": "/details/Berita-Pagi-Sabah-1:1028:42612269"
        },
        {
          "eventId": "35990805",
          "title": "Berita Pagi Sarawak",
          "programmeId": null,
          "episodeId": null,
          "datetime": "2021-01-28 07:45:00.0",
          "datetimeInUtc": "2021-01-27 23:45:00.0",
          "duration": "00:15:00",
          "siTrafficKey": "1:1028:42612270",
          "detailUrl": "/details/Berita-Pagi-Sarawak-1:1028:42612270"
        },
        {
          "eventId": "35990806",
          "title": "(L) Selamat Pagi Malaysia",
          "programmeId": null,
          "episodeId": null,
          "datetime": "2021-01-28 08:00:00.0",
          "datetimeInUtc": "2021-01-28 00:00:00.0",
          "duration": "02:00:00",
          "siTrafficKey": "1:1028:42612271",
          "detailUrl": "/details/L-Selamat-Pagi-Malaysia-1:1028:42612271"
        },
        {
          "eventId": "36165451",
          "title": "Jiwa Kacau",
          "programmeId": null,
          "episodeId": null,
          "datetime": "2021-01-28 10:00:00.0",
          "datetimeInUtc": "2021-01-28 02:00:00.0",
          "duration": "00:30:00",
          "siTrafficKey": "1:1028:42903876",
          "detailUrl": "/details/Jiwa-Kacau-1:1028:42903876"
        },
        {
          "eventId": "36165452",
          "title": "Nadi Cergas",
          "programmeId": null,
          "episodeId": null,
          "datetime": "2021-01-28 10:30:00.0",
          "datetimeInUtc": "2021-01-28 02:30:00.0",
          "duration": "00:30:00",
          "siTrafficKey": "1:1028:42903877",
          "detailUrl": "/details/Nadi-Cergas-1:1028:42903877"
        },
        {
          "eventId": "36165453",
          "title": "Gelak Sampai Kenyang",
          "programmeId": null,
          "episodeId": null,
          "datetime": "2021-01-28 11:00:00.0",
          "datetimeInUtc": "2021-01-28 03:00:00.0",
          "duration": "00:30:00",
          "siTrafficKey": "1:1028:42903878",
          "detailUrl": "/details/Gelak-Sampai-Kenyang-1:1028:42903878"
        },
        {
          "eventId": "35990808",
          "title": "Klik-Klik",
          "programmeId": null,
          "episodeId": null,
          "datetime": "2021-01-28 11:30:00.0",
          "datetimeInUtc": "2021-01-28 03:30:00.0",
          "duration": "00:30:00",
          "siTrafficKey": "1:1028:42612273",
          "detailUrl": "/details/Klik-Klik-1:1028:42612273"
        },
        {
          "eventId": "36165454",
          "title": "A Year in the Wild",
          "programmeId": null,
          "episodeId": null,
          "datetime": "2021-01-28 12:00:00.0",
          "datetimeInUtc": "2021-01-28 04:00:00.0",
          "duration": "01:00:00",
          "siTrafficKey": "1:1028:42903879",
          "detailUrl": "/details/A-Year-in-the-Wild-1:1028:42903879"
        },
        {
          "eventId": "35990810",
          "title": "Berita Tengah Hari",
          "programmeId": null,
          "episodeId": null,
          "datetime": "2021-01-28 13:00:00.0",
          "datetimeInUtc": "2021-01-28 05:00:00.0",
          "duration": "00:30:00",
          "siTrafficKey": "1:1028:42612275",
          "detailUrl": "/details/Berita-Tengah-Hari-1:1028:42612275"
        },
        {
          "eventId": "35990811",
          "title": "Skuad Chenta",
          "programmeId": null,
          "episodeId": null,
          "datetime": "2021-01-28 13:30:00.0",
          "datetimeInUtc": "2021-01-28 05:30:00.0",
          "duration": "00:30:00",
          "siTrafficKey": "1:1028:42612276",
          "detailUrl": "/details/Skuad-Chenta-1:1028:42612276"
        },
        {
          "eventId": "36165455",
          "title": "Anda Musykil",
          "programmeId": null,
          "episodeId": null,
          "datetime": "2021-01-28 14:00:00.0",
          "datetimeInUtc": "2021-01-28 06:00:00.0",
          "duration": "01:00:00",
          "siTrafficKey": "1:1028:42903880",
          "detailUrl": "/details/Anda-Musykil-1:1028:42903880"
        },
        {
          "eventId": "36165456",
          "title": "Mahligai Kaca",
          "programmeId": null,
          "episodeId": null,
          "datetime": "2021-01-28 15:00:00.0",
          "datetimeInUtc": "2021-01-28 07:00:00.0",
          "duration": "01:00:00",
          "siTrafficKey": "1:1028:42903881",
          "detailUrl": "/details/Mahligai-Kaca-1:1028:42903881"
        },
        {
          "eventId": "35990815",
          "title": "Agrotek",
          "programmeId": null,
          "episodeId": null,
          "datetime": "2021-01-28 16:00:00.0",
          "datetimeInUtc": "2021-01-28 08:00:00.0",
          "duration": "00:30:00",
          "siTrafficKey": "1:1028:42612280",
          "detailUrl": "/details/Agrotek-1:1028:42612280"
        },
        {
          "eventId": "35990816",
          "title": "Rona Sabah",
          "programmeId": null,
          "episodeId": null,
          "datetime": "2021-01-28 16:30:00.0",
          "datetimeInUtc": "2021-01-28 08:30:00.0",
          "duration": "00:30:00",
          "siTrafficKey": "1:1028:42612281",
          "detailUrl": "/details/Rona-Sabah-1:1028:42612281"
        },
        {
          "eventId": "35990817",
          "title": "Berita Wilayah",
          "programmeId": null,
          "episodeId": null,
          "datetime": "2021-01-28 17:00:00.0",
          "datetimeInUtc": "2021-01-28 09:00:00.0",
          "duration": "01:00:00",
          "siTrafficKey": "1:1028:42612282",
          "detailUrl": "/details/Berita-Wilayah-1:1028:42612282"
        },
        {
          "eventId": "36165457",
          "title": "Bakul Telur Emas",
          "programmeId": null,
          "episodeId": null,
          "datetime": "2021-01-28 18:00:00.0",
          "datetimeInUtc": "2021-01-28 10:00:00.0",
          "duration": "00:30:00",
          "siTrafficKey": "1:1028:42903882",
          "detailUrl": "/details/Bakul-Telur-Emas-1:1028:42903882"
        },
        {
          "eventId": "36165458",
          "title": "Usrah Hikmah",
          "programmeId": null,
          "episodeId": null,
          "datetime": "2021-01-28 18:30:00.0",
          "datetimeInUtc": "2021-01-28 10:30:00.0",
          "duration": "00:30:00",
          "siTrafficKey": "1:1028:42903883",
          "detailUrl": "/details/Usrah-Hikmah-1:1028:42903883"
        },
        {
          "eventId": "36165459",
          "title": "Nota Buat Cempaka",
          "programmeId": null,
          "episodeId": null,
          "datetime": "2021-01-28 19:00:00.0",
          "datetimeInUtc": "2021-01-28 11:00:00.0",
          "duration": "01:00:00",
          "siTrafficKey": "1:1028:42903884",
          "detailUrl": "/details/Nota-Buat-Cempaka-1:1028:42903884"
        },
        {
          "eventId": "35990821",
          "title": "Berita Perdana",
          "programmeId": null,
          "episodeId": null,
          "datetime": "2021-01-28 20:00:00.0",
          "datetimeInUtc": "2021-01-28 12:00:00.0",
          "duration": "01:00:00",
          "siTrafficKey": "1:1028:42612286",
          "detailUrl": "/details/Berita-Perdana-1:1028:42612286"
        },
        {
          "eventId": "35990822",
          "title": "Forum Perdana Ehwal Islam",
          "programmeId": null,
          "episodeId": null,
          "datetime": "2021-01-28 21:00:00.0",
          "datetimeInUtc": "2021-01-28 13:00:00.0",
          "duration": "01:00:00",
          "siTrafficKey": "1:1028:42612287",
          "detailUrl": "/details/Forum-Perdana-Ehwal-Islam-1:1028:42612287"
        },
        {
          "eventId": "36165460",
          "title": "Logika Alam",
          "programmeId": null,
          "episodeId": null,
          "datetime": "2021-01-28 22:00:00.0",
          "datetimeInUtc": "2021-01-28 14:00:00.0",
          "duration": "00:30:00",
          "siTrafficKey": "1:1028:42903885",
          "detailUrl": "/details/Logika-Alam-1:1028:42903885"
        },
        {
          "eventId": "36165461",
          "title": "Buaian Kasih",
          "programmeId": null,
          "episodeId": null,
          "datetime": "2021-01-28 22:30:00.0",
          "datetimeInUtc": "2021-01-28 14:30:00.0",
          "duration": "00:30:00",
          "siTrafficKey": "1:1028:42903886",
          "detailUrl": "/details/Buaian-Kasih-1:1028:42903886"
        },
        {
          "eventId": "35990825",
          "title": "Berita Dunia",
          "programmeId": null,
          "episodeId": null,
          "datetime": "2021-01-28 23:00:00.0",
          "datetimeInUtc": "2021-01-28 15:00:00.0",
          "duration": "00:30:00",
          "siTrafficKey": "1:1028:42612290",
          "detailUrl": "/details/Berita-Dunia-1:1028:42612290"
        },
        {
          "eventId": "36165462",
          "title": "ATP Uncovered",
          "programmeId": null,
          "episodeId": null,
          "datetime": "2021-01-28 23:30:00.0",
          "datetimeInUtc": "2021-01-28 15:30:00.0",
          "duration": "00:30:00",
          "siTrafficKey": "1:1028:42903887",
          "detailUrl": "/details/ATP-Uncovered-1:1028:42903887"
        }
      ],
      "2021-01-29": [
        {
          "eventId": "35990827",
          "title": "Berita Tengah Malam",
          "programmeId": null,
          "episodeId": null,
          "datetime": "2021-01-29 00:00:00.0",
          "datetimeInUtc": "2021-01-28 16:00:00.0",
          "duration": "00:30:00",
          "siTrafficKey": "1:1028:42612292",
          "detailUrl": "/details/Berita-Tengah-Malam-1:1028:42612292"
        },
        {
          "eventId": "36165463",
          "title": "Trans World Sports",
          "programmeId": null,
          "episodeId": null,
          "datetime": "2021-01-29 00:30:00.0",
          "datetimeInUtc": "2021-01-28 16:30:00.0",
          "duration": "01:00:00",
          "siTrafficKey": "1:1028:42903888",
          "detailUrl": "/details/Trans-World-Sports-1:1028:42903888"
        },
        {
          "eventId": "35990830",
          "title": "Panorama",
          "programmeId": null,
          "episodeId": null,
          "datetime": "2021-01-29 01:30:00.0",
          "datetimeInUtc": "2021-01-28 17:30:00.0",
          "duration": "00:30:00",
          "siTrafficKey": "1:1028:42612295",
          "detailUrl": "/details/Panorama-1:1028:42612295"
        },
        {
          "eventId": "36165464",
          "title": "Cucu Wan Lebor",
          "programmeId": null,
          "episodeId": null,
          "datetime": "2021-01-29 02:00:00.0",
          "datetimeInUtc": "2021-01-28 18:00:00.0",
          "duration": "00:30:00",
          "siTrafficKey": "1:1028:42903889",
          "detailUrl": "/details/Cucu-Wan-Lebor-1:1028:42903889"
        },
        {
          "eventId": "35990832",
          "title": "Skuad Chenta",
          "programmeId": null,
          "episodeId": null,
          "datetime": "2021-01-29 02:30:00.0",
          "datetimeInUtc": "2021-01-28 18:30:00.0",
          "duration": "00:30:00",
          "siTrafficKey": "1:1028:42612297",
          "detailUrl": "/details/Skuad-Chenta-1:1028:42612297"
        },
        {
          "eventId": "36165465",
          "title": "Gelak Sampai Kenyang",
          "programmeId": null,
          "episodeId": null,
          "datetime": "2021-01-29 03:00:00.0",
          "datetimeInUtc": "2021-01-28 19:00:00.0",
          "duration": "00:30:00",
          "siTrafficKey": "1:1028:42903890",
          "detailUrl": "/details/Gelak-Sampai-Kenyang-1:1028:42903890"
        },
        {
          "eventId": "36165466",
          "title": "Dari Mata Arisa",
          "programmeId": null,
          "episodeId": null,
          "datetime": "2021-01-29 03:30:00.0",
          "datetimeInUtc": "2021-01-28 19:30:00.0",
          "duration": "01:00:00",
          "siTrafficKey": "1:1028:42903891",
          "detailUrl": "/details/Dari-Mata-Arisa-1:1028:42903891"
        },
        {
          "eventId": "36165467",
          "title": "Bakul Telur Emas",
          "programmeId": null,
          "episodeId": null,
          "datetime": "2021-01-29 04:30:00.0",
          "datetimeInUtc": "2021-01-28 20:30:00.0",
          "duration": "00:30:00",
          "siTrafficKey": "1:1028:42903892",
          "detailUrl": "/details/Bakul-Telur-Emas-1:1028:42903892"
        },
        {
          "eventId": "36165468",
          "title": "Mahligai Kaca",
          "programmeId": null,
          "episodeId": null,
          "datetime": "2021-01-29 05:00:00.0",
          "datetimeInUtc": "2021-01-28 21:00:00.0",
          "duration": "01:00:00",
          "siTrafficKey": "1:1028:42903893",
          "detailUrl": "/details/Mahligai-Kaca-1:1028:42903893"
        },
        {
          "eventId": "36165469",
          "title": "Anda Musykil",
          "programmeId": null,
          "episodeId": null,
          "datetime": "2021-01-29 06:00:00.0",
          "datetimeInUtc": "2021-01-28 22:00:00.0",
          "duration": "01:00:00",
          "siTrafficKey": "1:1028:42903894",
          "detailUrl": "/details/Anda-Musykil-1:1028:42903894"
        },
        {
          "eventId": "36004899",
          "title": "Berita Pagi",
          "programmeId": null,
          "episodeId": null,
          "datetime": "2021-01-29 07:00:00.0",
          "datetimeInUtc": "2021-01-28 23:00:00.0",
          "duration": "00:30:00",
          "siTrafficKey": "1:1028:42612303",
          "detailUrl": "/details/Berita-Pagi-1:1028:42612303"
        },
        {
          "eventId": "36004900",
          "title": "Berita Pagi Sabah",
          "programmeId": null,
          "episodeId": null,
          "datetime": "2021-01-29 07:30:00.0",
          "datetimeInUtc": "2021-01-28 23:30:00.0",
          "duration": "00:15:00",
          "siTrafficKey": "1:1028:42612304",
          "detailUrl": "/details/Berita-Pagi-Sabah-1:1028:42612304"
        },
        {
          "eventId": "36004901",
          "title": "Berita Pagi Sarawak",
          "programmeId": null,
          "episodeId": null,
          "datetime": "2021-01-29 07:45:00.0",
          "datetimeInUtc": "2021-01-28 23:45:00.0",
          "duration": "00:15:00",
          "siTrafficKey": "1:1028:42612305",
          "detailUrl": "/details/Berita-Pagi-Sarawak-1:1028:42612305"
        },
        {
          "eventId": "36004902",
          "title": "(L) Selamat Pagi Malaysia",
          "programmeId": null,
          "episodeId": null,
          "datetime": "2021-01-29 08:00:00.0",
          "datetimeInUtc": "2021-01-29 00:00:00.0",
          "duration": "02:00:00",
          "siTrafficKey": "1:1028:42612306",
          "detailUrl": "/details/L-Selamat-Pagi-Malaysia-1:1028:42612306"
        },
        {
          "eventId": "36165470",
          "title": "Operation Ouch!",
          "programmeId": null,
          "episodeId": null,
          "datetime": "2021-01-29 10:00:00.0",
          "datetimeInUtc": "2021-01-29 02:00:00.0",
          "duration": "00:30:00",
          "siTrafficKey": "1:1028:42903895",
          "detailUrl": "/details/Operation-Ouch-1:1028:42903895"
        },
        {
          "eventId": "36165471",
          "title": "Jungle Book",
          "programmeId": null,
          "episodeId": null,
          "datetime": "2021-01-29 10:30:00.0",
          "datetimeInUtc": "2021-01-29 02:30:00.0",
          "duration": "00:30:00",
          "siTrafficKey": "1:1028:42903896",
          "detailUrl": "/details/Jungle-Book-1:1028:42903896"
        },
        {
          "eventId": "36165472",
          "title": "Tilawah Interaktif",
          "programmeId": null,
          "episodeId": null,
          "datetime": "2021-01-29 11:00:00.0",
          "datetimeInUtc": "2021-01-29 03:00:00.0",
          "duration": "01:00:00",
          "siTrafficKey": "1:1028:42903897",
          "detailUrl": "/details/Tilawah-Interaktif-1:1028:42903897"
        },
        {
          "eventId": "36004904",
          "title": "Berita Tengah Hari",
          "programmeId": null,
          "episodeId": null,
          "datetime": "2021-01-29 12:00:00.0",
          "datetimeInUtc": "2021-01-29 04:00:00.0",
          "duration": "00:15:00",
          "siTrafficKey": "1:1028:42612308",
          "detailUrl": "/details/Berita-Tengah-Hari-1:1028:42612308"
        },
        {
          "eventId": "36165473",
          "title": "Jelajah Hati",
          "programmeId": null,
          "episodeId": null,
          "datetime": "2021-01-29 12:15:00.0",
          "datetimeInUtc": "2021-01-29 04:15:00.0",
          "duration": "00:30:00",
          "siTrafficKey": "1:1028:42903898",
          "detailUrl": "/details/Jelajah-Hati-1:1028:42903898"
        },
        {
          "eventId": "36165474",
          "title": "Not Available",
          "programmeId": null,
          "episodeId": null,
          "datetime": "2021-01-29 12:45:00.0",
          "datetimeInUtc": "2021-01-29 04:45:00.0",
          "duration": "00:15:00",
          "siTrafficKey": "1:1028:42903899",
          "detailUrl": "/details/Not-Available-1:1028:42903899"
        },
        {
          "eventId": "36165475",
          "title": "Mau'izah",
          "programmeId": null,
          "episodeId": null,
          "datetime": "2021-01-29 13:00:00.0",
          "datetimeInUtc": "2021-01-29 05:00:00.0",
          "duration": "01:00:00",
          "siTrafficKey": "1:1028:42903900",
          "detailUrl": "/details/Mauizah-1:1028:42903900"
        },
        {
          "eventId": "36165477",
          "title": "Forum Perdana Ehwal Islam",
          "programmeId": null,
          "episodeId": null,
          "datetime": "2021-01-29 14:00:00.0",
          "datetimeInUtc": "2021-01-29 06:00:00.0",
          "duration": "01:00:00",
          "siTrafficKey": "1:1028:42903902",
          "detailUrl": "/details/Forum-Perdana-Ehwal-Islam-1:1028:42903902"
        },
        {
          "eventId": "36165478",
          "title": "Mahligai Kaca",
          "programmeId": null,
          "episodeId": null,
          "datetime": "2021-01-29 15:00:00.0",
          "datetimeInUtc": "2021-01-29 07:00:00.0",
          "duration": "01:00:00",
          "siTrafficKey": "1:1028:42903903",
          "detailUrl": "/details/Mahligai-Kaca-1:1028:42903903"
        },
        {
          "eventId": "36165479",
          "title": "Santri Serumpun",
          "programmeId": null,
          "episodeId": null,
          "datetime": "2021-01-29 16:00:00.0",
          "datetimeInUtc": "2021-01-29 08:00:00.0",
          "duration": "00:30:00",
          "siTrafficKey": "1:1028:42903904",
          "detailUrl": "/details/Santri-Serumpun-1:1028:42903904"
        },
        {
          "eventId": "36004913",
          "title": "Simfoni Alam",
          "programmeId": null,
          "episodeId": null,
          "datetime": "2021-01-29 16:30:00.0",
          "datetimeInUtc": "2021-01-29 08:30:00.0",
          "duration": "00:30:00",
          "siTrafficKey": "1:1028:42612317",
          "detailUrl": "/details/Simfoni-Alam-1:1028:42612317"
        },
        {
          "eventId": "36004914",
          "title": "Berita Wilayah",
          "programmeId": null,
          "episodeId": null,
          "datetime": "2021-01-29 17:00:00.0",
          "datetimeInUtc": "2021-01-29 09:00:00.0",
          "duration": "01:00:00",
          "siTrafficKey": "1:1028:42612318",
          "detailUrl": "/details/Berita-Wilayah-1:1028:42612318"
        },
        {
          "eventId": "36165480",
          "title": "Info Medika",
          "programmeId": null,
          "episodeId": null,
          "datetime": "2021-01-29 18:00:00.0",
          "datetimeInUtc": "2021-01-29 10:00:00.0",
          "duration": "00:30:00",
          "siTrafficKey": "1:1028:42903905",
          "detailUrl": "/details/Info-Medika-1:1028:42903905"
        },
        {
          "eventId": "36165482",
          "title": "Ilmu Aqaaid",
          "programmeId": null,
          "episodeId": null,
          "datetime": "2021-01-29 18:30:00.0",
          "datetimeInUtc": "2021-01-29 10:30:00.0",
          "duration": "00:30:00",
          "siTrafficKey": "1:1028:42903907",
          "detailUrl": "/details/Ilmu-Aqaaid-1:1028:42903907"
        },
        {
          "eventId": "36165483",
          "title": "Nota Buat Cempaka",
          "programmeId": null,
          "episodeId": null,
          "datetime": "2021-01-29 19:00:00.0",
          "datetimeInUtc": "2021-01-29 11:00:00.0",
          "duration": "01:00:00",
          "siTrafficKey": "1:1028:42903908",
          "detailUrl": "/details/Nota-Buat-Cempaka-1:1028:42903908"
        },
        {
          "eventId": "36004919",
          "title": "Berita Perdana",
          "programmeId": null,
          "episodeId": null,
          "datetime": "2021-01-29 20:00:00.0",
          "datetimeInUtc": "2021-01-29 12:00:00.0",
          "duration": "01:00:00",
          "siTrafficKey": "1:1028:42612323",
          "detailUrl": "/details/Berita-Perdana-1:1028:42612323"
        },
        {
          "eventId": "36004920",
          "title": "Not Available",
          "programmeId": null,
          "episodeId": null,
          "datetime": "2021-01-29 21:00:00.0",
          "datetimeInUtc": "2021-01-29 13:00:00.0",
          "duration": "01:00:00",
          "siTrafficKey": "1:1028:42612324",
          "detailUrl": "/details/Not-Available-1:1028:42612324"
        },
        {
          "eventId": "36165484",
          "title": "Singgah Di Agro",
          "programmeId": null,
          "episodeId": null,
          "datetime": "2021-01-29 22:00:00.0",
          "datetimeInUtc": "2021-01-29 14:00:00.0",
          "duration": "00:30:00",
          "siTrafficKey": "1:1028:42903909",
          "detailUrl": "/details/Singgah-Di-Agro-1:1028:42903909"
        },
        {
          "eventId": "36004922",
          "title": "Agropreneur Muda",
          "programmeId": null,
          "episodeId": null,
          "datetime": "2021-01-29 22:30:00.0",
          "datetimeInUtc": "2021-01-29 14:30:00.0",
          "duration": "00:30:00",
          "siTrafficKey": "1:1028:42612326",
          "detailUrl": "/details/Agropreneur-Muda-1:1028:42612326"
        },
        {
          "eventId": "36004923",
          "title": "Berita Dunia",
          "programmeId": null,
          "episodeId": null,
          "datetime": "2021-01-29 23:00:00.0",
          "datetimeInUtc": "2021-01-29 15:00:00.0",
          "duration": "00:30:00",
          "siTrafficKey": "1:1028:42612327",
          "detailUrl": "/details/Berita-Dunia-1:1028:42612327"
        },
        {
          "eventId": "36165485",
          "title": "ATP Uncovered",
          "programmeId": null,
          "episodeId": null,
          "datetime": "2021-01-29 23:30:00.0",
          "datetimeInUtc": "2021-01-29 15:30:00.0",
          "duration": "00:30:00",
          "siTrafficKey": "1:1028:42903910",
          "detailUrl": "/details/ATP-Uncovered-1:1028:42903910"
        }
      ],
      "2021-01-30": [
        {
          "eventId": "36004925",
          "title": "Berita Tengah Malam",
          "programmeId": null,
          "episodeId": null,
          "datetime": "2021-01-30 00:00:00.0",
          "datetimeInUtc": "2021-01-29 16:00:00.0",
          "duration": "00:30:00",
          "siTrafficKey": "1:1028:42612329",
          "detailUrl": "/details/Berita-Tengah-Malam-1:1028:42612329"
        },
        {
          "eventId": "36004926",
          "title": "Not Available",
          "programmeId": null,
          "episodeId": null,
          "datetime": "2021-01-30 00:30:00.0",
          "datetimeInUtc": "2021-01-29 16:30:00.0",
          "duration": "00:15:00",
          "siTrafficKey": "1:1028:42612330",
          "detailUrl": "/details/Not-Available-1:1028:42612330"
        },
        {
          "eventId": "36004928",
          "title": "Mau'izah",
          "programmeId": null,
          "episodeId": null,
          "datetime": "2021-01-30 00:45:00.0",
          "datetimeInUtc": "2021-01-29 16:45:00.0",
          "duration": "00:45:00",
          "siTrafficKey": "1:1028:42612332",
          "detailUrl": "/details/Mauizah-1:1028:42612332"
        },
        {
          "eventId": "36004929",
          "title": "Simfoni Alam",
          "programmeId": null,
          "episodeId": null,
          "datetime": "2021-01-30 01:30:00.0",
          "datetimeInUtc": "2021-01-29 17:30:00.0",
          "duration": "00:30:00",
          "siTrafficKey": "1:1028:42612333",
          "detailUrl": "/details/Simfoni-Alam-1:1028:42612333"
        },
        {
          "eventId": "36165486",
          "title": "Cucu Wan Lebor",
          "programmeId": null,
          "episodeId": null,
          "datetime": "2021-01-30 02:00:00.0",
          "datetimeInUtc": "2021-01-29 18:00:00.0",
          "duration": "00:30:00",
          "siTrafficKey": "1:1028:42903911",
          "detailUrl": "/details/Cucu-Wan-Lebor-1:1028:42903911"
        },
        {
          "eventId": "36004931",
          "title": "Santri Serumpun",
          "programmeId": null,
          "episodeId": null,
          "datetime": "2021-01-30 02:30:00.0",
          "datetimeInUtc": "2021-01-29 18:30:00.0",
          "duration": "00:30:00",
          "siTrafficKey": "1:1028:42612335",
          "detailUrl": "/details/Santri-Serumpun-1:1028:42612335"
        },
        {
          "eventId": "36004932",
          "title": "Jelajah Hati",
          "programmeId": null,
          "episodeId": null,
          "datetime": "2021-01-30 03:00:00.0",
          "datetimeInUtc": "2021-01-29 19:00:00.0",
          "duration": "00:30:00",
          "siTrafficKey": "1:1028:42612336",
          "detailUrl": "/details/Jelajah-Hati-1:1028:42612336"
        },
        {
          "eventId": "36165487",
          "title": "Singgah Di Agro",
          "programmeId": null,
          "episodeId": null,
          "datetime": "2021-01-30 03:30:00.0",
          "datetimeInUtc": "2021-01-29 19:30:00.0",
          "duration": "00:30:00",
          "siTrafficKey": "1:1028:42903912",
          "detailUrl": "/details/Singgah-Di-Agro-1:1028:42903912"
        },
        {
          "eventId": "36165488",
          "title": "Destinasi Agung",
          "programmeId": null,
          "episodeId": null,
          "datetime": "2021-01-30 04:00:00.0",
          "datetimeInUtc": "2021-01-29 20:00:00.0",
          "duration": "00:30:00",
          "siTrafficKey": "1:1028:42903913",
          "detailUrl": "/details/Destinasi-Agung-1:1028:42903913"
        },
        {
          "eventId": "36165489",
          "title": "Bakul Telur Emas",
          "programmeId": null,
          "episodeId": null,
          "datetime": "2021-01-30 04:30:00.0",
          "datetimeInUtc": "2021-01-29 20:30:00.0",
          "duration": "00:30:00",
          "siTrafficKey": "1:1028:42903914",
          "detailUrl": "/details/Bakul-Telur-Emas-1:1028:42903914"
        },
        {
          "eventId": "36165490",
          "title": "Mahligai Kaca",
          "programmeId": null,
          "episodeId": null,
          "datetime": "2021-01-30 05:00:00.0",
          "datetimeInUtc": "2021-01-29 21:00:00.0",
          "duration": "00:45:00",
          "siTrafficKey": "1:1028:42903915",
          "detailUrl": "/details/Mahligai-Kaca-1:1028:42903915"
        },
        {
          "eventId": "36193927",
          "title": "Feminin Waja",
          "programmeId": null,
          "episodeId": null,
          "datetime": "2021-01-30 05:45:00.0",
          "datetimeInUtc": "2021-01-29 21:45:00.0",
          "duration": "00:15:00",
          "siTrafficKey": "1:1028:42964907",
          "detailUrl": "/details/Feminin-Waja-1:1028:42964907"
        },
        {
          "eventId": "36176380",
          "title": "Tilawah Interaktif",
          "programmeId": null,
          "episodeId": null,
          "datetime": "2021-01-30 06:00:00.0",
          "datetimeInUtc": "2021-01-29 22:00:00.0",
          "duration": "01:00:00",
          "siTrafficKey": "1:1028:42903916",
          "detailUrl": "/details/Tilawah-Interaktif-1:1028:42903916"
        },
        {
          "eventId": "36017485",
          "title": "Berita Pagi",
          "programmeId": null,
          "episodeId": null,
          "datetime": "2021-01-30 07:00:00.0",
          "datetimeInUtc": "2021-01-29 23:00:00.0",
          "duration": "00:30:00",
          "siTrafficKey": "1:1028:42612343",
          "detailUrl": "/details/Berita-Pagi-1:1028:42612343"
        },
        {
          "eventId": "36017486",
          "title": "Berita Pagi Sabah",
          "programmeId": null,
          "episodeId": null,
          "datetime": "2021-01-30 07:30:00.0",
          "datetimeInUtc": "2021-01-29 23:30:00.0",
          "duration": "00:15:00",
          "siTrafficKey": "1:1028:42612344",
          "detailUrl": "/details/Berita-Pagi-Sabah-1:1028:42612344"
        },
        {
          "eventId": "36017487",
          "title": "Berita Pagi Sarawak",
          "programmeId": null,
          "episodeId": null,
          "datetime": "2021-01-30 07:45:00.0",
          "datetimeInUtc": "2021-01-29 23:45:00.0",
          "duration": "00:15:00",
          "siTrafficKey": "1:1028:42612345",
          "detailUrl": "/details/Berita-Pagi-Sarawak-1:1028:42612345"
        },
        {
          "eventId": "36017488",
          "title": "(L) Selamat Pagi Malaysia",
          "programmeId": null,
          "episodeId": null,
          "datetime": "2021-01-30 08:00:00.0",
          "datetimeInUtc": "2021-01-30 00:00:00.0",
          "duration": "02:00:00",
          "siTrafficKey": "1:1028:42612346",
          "detailUrl": "/details/L-Selamat-Pagi-Malaysia-1:1028:42612346"
        },
        {
          "eventId": "36176381",
          "title": "Operation Ouch!",
          "programmeId": null,
          "episodeId": null,
          "datetime": "2021-01-30 10:00:00.0",
          "datetimeInUtc": "2021-01-30 02:00:00.0",
          "duration": "00:30:00",
          "siTrafficKey": "1:1028:42903917",
          "detailUrl": "/details/Operation-Ouch-1:1028:42903917"
        },
        {
          "eventId": "36176382",
          "title": "Jungle Book",
          "programmeId": null,
          "episodeId": null,
          "datetime": "2021-01-30 10:30:00.0",
          "datetimeInUtc": "2021-01-30 02:30:00.0",
          "duration": "00:30:00",
          "siTrafficKey": "1:1028:42903918",
          "detailUrl": "/details/Jungle-Book-1:1028:42903918"
        },
        {
          "eventId": "36176383",
          "title": "Pesona XY",
          "programmeId": null,
          "episodeId": null,
          "datetime": "2021-01-30 11:00:00.0",
          "datetimeInUtc": "2021-01-30 03:00:00.0",
          "duration": "01:00:00",
          "siTrafficKey": "1:1028:42903919",
          "detailUrl": "/details/Pesona-XY-1:1028:42903919"
        },
        {
          "eventId": "36176384",
          "title": "Visi Intelek",
          "programmeId": null,
          "episodeId": null,
          "datetime": "2021-01-30 12:00:00.0",
          "datetimeInUtc": "2021-01-30 04:00:00.0",
          "duration": "00:30:00",
          "siTrafficKey": "1:1028:42903920",
          "detailUrl": "/details/Visi-Intelek-1:1028:42903920"
        },
        {
          "eventId": "36176385",
          "title": "Ekspresi Muzikku",
          "programmeId": null,
          "episodeId": null,
          "datetime": "2021-01-30 12:30:00.0",
          "datetimeInUtc": "2021-01-30 04:30:00.0",
          "duration": "00:30:00",
          "siTrafficKey": "1:1028:42903921",
          "detailUrl": "/details/Ekspresi-Muzikku-1:1028:42903921"
        },
        {
          "eventId": "36017493",
          "title": "Berita Tengah Hari",
          "programmeId": null,
          "episodeId": null,
          "datetime": "2021-01-30 13:00:00.0",
          "datetimeInUtc": "2021-01-30 05:00:00.0",
          "duration": "00:30:00",
          "siTrafficKey": "1:1028:42612351",
          "detailUrl": "/details/Berita-Tengah-Hari-1:1028:42612351"
        },
        {
          "eventId": "36176386",
          "title": "Logika Alam",
          "programmeId": null,
          "episodeId": null,
          "datetime": "2021-01-30 13:30:00.0",
          "datetimeInUtc": "2021-01-30 05:30:00.0",
          "duration": "00:30:00",
          "siTrafficKey": "1:1028:42903922",
          "detailUrl": "/details/Logika-Alam-1:1028:42903922"
        },
        {
          "eventId": "36176387",
          "title": "Impak Aksi",
          "programmeId": null,
          "episodeId": null,
          "datetime": "2021-01-30 14:00:00.0",
          "datetimeInUtc": "2021-01-30 06:00:00.0",
          "duration": "00:30:00",
          "siTrafficKey": "1:1028:42903923",
          "detailUrl": "/details/Impak-Aksi-1:1028:42903923"
        },
        {
          "eventId": "36176388",
          "title": "X-Sikap",
          "programmeId": null,
          "episodeId": null,
          "datetime": "2021-01-30 14:30:00.0",
          "datetimeInUtc": "2021-01-30 06:30:00.0",
          "duration": "00:30:00",
          "siTrafficKey": "1:1028:42903924",
          "detailUrl": "/details/X-Sikap-1:1028:42903924"
        },
        {
          "eventId": "36176389",
          "title": "Usung Putih",
          "programmeId": null,
          "episodeId": null,
          "datetime": "2021-01-30 15:00:00.0",
          "datetimeInUtc": "2021-01-30 07:00:00.0",
          "duration": "02:00:00",
          "siTrafficKey": "1:1028:42903925",
          "detailUrl": "/details/Usung-Putih-1:1028:42903925"
        },
        {
          "eventId": "36017498",
          "title": "Berita Wilayah",
          "programmeId": null,
          "episodeId": null,
          "datetime": "2021-01-30 17:00:00.0",
          "datetimeInUtc": "2021-01-30 09:00:00.0",
          "duration": "01:00:00",
          "siTrafficKey": "1:1028:42612356",
          "detailUrl": "/details/Berita-Wilayah-1:1028:42612356"
        },
        {
          "eventId": "36176390",
          "title": "Agrotek",
          "programmeId": null,
          "episodeId": null,
          "datetime": "2021-01-30 18:00:00.0",
          "datetimeInUtc": "2021-01-30 10:00:00.0",
          "duration": "00:15:00",
          "siTrafficKey": "1:1028:42903926",
          "detailUrl": "/details/Agrotek-1:1028:42903926"
        },
        {
          "eventId": "36017500",
          "title": "(L) Sidang Media COVID-19",
          "programmeId": null,
          "episodeId": null,
          "datetime": "2021-01-30 18:15:00.0",
          "datetimeInUtc": "2021-01-30 10:15:00.0",
          "duration": "00:15:00",
          "siTrafficKey": "1:1028:42612358",
          "detailUrl": "/details/L-Sidang-Media-COVID-19-1:1028:42612358"
        },
        {
          "eventId": "36017501",
          "title": "Muqaddam",
          "programmeId": null,
          "episodeId": null,
          "datetime": "2021-01-30 18:30:00.0",
          "datetimeInUtc": "2021-01-30 10:30:00.0",
          "duration": "00:30:00",
          "siTrafficKey": "1:1028:42612359",
          "detailUrl": "/details/Muqaddam-1:1028:42612359"
        },
        {
          "eventId": "36176391",
          "title": "Nota Buat Cempaka",
          "programmeId": null,
          "episodeId": null,
          "datetime": "2021-01-30 19:00:00.0",
          "datetimeInUtc": "2021-01-30 11:00:00.0",
          "duration": "01:00:00",
          "siTrafficKey": "1:1028:42903927",
          "detailUrl": "/details/Nota-Buat-Cempaka-1:1028:42903927"
        },
        {
          "eventId": "36017503",
          "title": "Berita Perdana",
          "programmeId": null,
          "episodeId": null,
          "datetime": "2021-01-30 20:00:00.0",
          "datetimeInUtc": "2021-01-30 12:00:00.0",
          "duration": "01:00:00",
          "siTrafficKey": "1:1028:42612361",
          "detailUrl": "/details/Berita-Perdana-1:1028:42612361"
        },
        {
          "eventId": "36176392",
          "title": "Ikhlas",
          "programmeId": null,
          "episodeId": null,
          "datetime": "2021-01-30 21:00:00.0",
          "datetimeInUtc": "2021-01-30 13:00:00.0",
          "duration": "02:00:00",
          "siTrafficKey": "1:1028:42903928",
          "detailUrl": "/details/Ikhlas-1:1028:42903928"
        },
        {
          "eventId": "36176393",
          "title": "Istimewa Bersama",
          "programmeId": null,
          "episodeId": null,
          "datetime": "2021-01-30 23:00:00.0",
          "datetimeInUtc": "2021-01-30 15:00:00.0",
          "duration": "01:00:00",
          "siTrafficKey": "1:1028:42903929",
          "detailUrl": "/details/Istimewa-Bersama-1:1028:42903929"
        }
      ],
      "2021-01-31": [
        {
          "eventId": "36017506",
          "title": "Berita Tengah Malam",
          "programmeId": null,
          "episodeId": null,
          "datetime": "2021-01-31 00:00:00.0",
          "datetimeInUtc": "2021-01-30 16:00:00.0",
          "duration": "00:30:00",
          "siTrafficKey": "1:1028:42612364",
          "detailUrl": "/details/Berita-Tengah-Malam-1:1028:42612364"
        },
        {
          "eventId": "36176394",
          "title": "Trans World Sports",
          "programmeId": null,
          "episodeId": null,
          "datetime": "2021-01-31 00:30:00.0",
          "datetimeInUtc": "2021-01-30 16:30:00.0",
          "duration": "01:00:00",
          "siTrafficKey": "1:1028:42903930",
          "detailUrl": "/details/Trans-World-Sports-1:1028:42903930"
        },
        {
          "eventId": "36017508",
          "title": "Rona Sabah",
          "programmeId": null,
          "episodeId": null,
          "datetime": "2021-01-31 01:30:00.0",
          "datetimeInUtc": "2021-01-30 17:30:00.0",
          "duration": "00:30:00",
          "siTrafficKey": "1:1028:42612366",
          "detailUrl": "/details/Rona-Sabah-1:1028:42612366"
        },
        {
          "eventId": "36176395",
          "title": "Cucu Wan Lebor",
          "programmeId": null,
          "episodeId": null,
          "datetime": "2021-01-31 02:00:00.0",
          "datetimeInUtc": "2021-01-30 18:00:00.0",
          "duration": "00:30:00",
          "siTrafficKey": "1:1028:42903931",
          "detailUrl": "/details/Cucu-Wan-Lebor-1:1028:42903931"
        },
        {
          "eventId": "36017510",
          "title": "Agrotek",
          "programmeId": null,
          "episodeId": null,
          "datetime": "2021-01-31 02:30:00.0",
          "datetimeInUtc": "2021-01-30 18:30:00.0",
          "duration": "00:30:00",
          "siTrafficKey": "1:1028:42612368",
          "detailUrl": "/details/Agrotek-1:1028:42612368"
        },
        {
          "eventId": "36176396",
          "title": "Kampuspedia",
          "programmeId": null,
          "episodeId": null,
          "datetime": "2021-01-31 03:00:00.0",
          "datetimeInUtc": "2021-01-30 19:00:00.0",
          "duration": "00:30:00",
          "siTrafficKey": "1:1028:42903932",
          "detailUrl": "/details/Kampuspedia-1:1028:42903932"
        },
        {
          "eventId": "36176397",
          "title": "Ekspresi Muzikku",
          "programmeId": null,
          "episodeId": null,
          "datetime": "2021-01-31 03:30:00.0",
          "datetimeInUtc": "2021-01-30 19:30:00.0",
          "duration": "00:30:00",
          "siTrafficKey": "1:1028:42903933",
          "detailUrl": "/details/Ekspresi-Muzikku-1:1028:42903933"
        },
        {
          "eventId": "36176398",
          "title": "Ikhlas",
          "programmeId": null,
          "episodeId": null,
          "datetime": "2021-01-31 04:00:00.0",
          "datetimeInUtc": "2021-01-30 20:00:00.0",
          "duration": "02:00:00",
          "siTrafficKey": "1:1028:42903934",
          "detailUrl": "/details/Ikhlas-1:1028:42903934"
        },
        {
          "eventId": "36182706",
          "title": "Ilmu Aqaaid",
          "programmeId": null,
          "episodeId": null,
          "datetime": "2021-01-31 06:00:00.0",
          "datetimeInUtc": "2021-01-30 22:00:00.0",
          "duration": "00:30:00",
          "siTrafficKey": "1:1028:42903935",
          "detailUrl": "/details/Ilmu-Aqaaid-1:1028:42903935"
        },
        {
          "eventId": "36031890",
          "title": "Panorama",
          "programmeId": null,
          "episodeId": null,
          "datetime": "2021-01-31 06:30:00.0",
          "datetimeInUtc": "2021-01-30 22:30:00.0",
          "duration": "00:30:00",
          "siTrafficKey": "1:1028:42612373",
          "detailUrl": "/details/Panorama-1:1028:42612373"
        },
        {
          "eventId": "36031891",
          "title": "Berita Pagi",
          "programmeId": null,
          "episodeId": null,
          "datetime": "2021-01-31 07:00:00.0",
          "datetimeInUtc": "2021-01-30 23:00:00.0",
          "duration": "00:30:00",
          "siTrafficKey": "1:1028:42612374",
          "detailUrl": "/details/Berita-Pagi-1:1028:42612374"
        },
        {
          "eventId": "36031892",
          "title": "Berita Pagi Sabah",
          "programmeId": null,
          "episodeId": null,
          "datetime": "2021-01-31 07:30:00.0",
          "datetimeInUtc": "2021-01-30 23:30:00.0",
          "duration": "00:15:00",
          "siTrafficKey": "1:1028:42612375",
          "detailUrl": "/details/Berita-Pagi-Sabah-1:1028:42612375"
        },
        {
          "eventId": "36031893",
          "title": "Berita Pagi Sarawak",
          "programmeId": null,
          "episodeId": null,
          "datetime": "2021-01-31 07:45:00.0",
          "datetimeInUtc": "2021-01-30 23:45:00.0",
          "duration": "00:15:00",
          "siTrafficKey": "1:1028:42612376",
          "detailUrl": "/details/Berita-Pagi-Sarawak-1:1028:42612376"
        },
        {
          "eventId": "36031894",
          "title": "(L) Selamat Pagi Malaysia",
          "programmeId": null,
          "episodeId": null,
          "datetime": "2021-01-31 08:00:00.0",
          "datetimeInUtc": "2021-01-31 00:00:00.0",
          "duration": "02:00:00",
          "siTrafficKey": "1:1028:42612377",
          "detailUrl": "/details/L-Selamat-Pagi-Malaysia-1:1028:42612377"
        },
        {
          "eventId": "36182707",
          "title": "Operation Ouch!",
          "programmeId": null,
          "episodeId": null,
          "datetime": "2021-01-31 10:00:00.0",
          "datetimeInUtc": "2021-01-31 02:00:00.0",
          "duration": "00:30:00",
          "siTrafficKey": "1:1028:42903936",
          "detailUrl": "/details/Operation-Ouch-1:1028:42903936"
        },
        {
          "eventId": "36182708",
          "title": "Jungle Book",
          "programmeId": null,
          "episodeId": null,
          "datetime": "2021-01-31 10:30:00.0",
          "datetimeInUtc": "2021-01-31 02:30:00.0",
          "duration": "00:30:00",
          "siTrafficKey": "1:1028:42903937",
          "detailUrl": "/details/Jungle-Book-1:1028:42903937"
        },
        {
          "eventId": "36182709",
          "title": "Rentak Jalanan",
          "programmeId": null,
          "episodeId": null,
          "datetime": "2021-01-31 11:00:00.0",
          "datetimeInUtc": "2021-01-31 03:00:00.0",
          "duration": "00:30:00",
          "siTrafficKey": "1:1028:42903938",
          "detailUrl": "/details/Rentak-Jalanan-1:1028:42903938"
        },
        {
          "eventId": "36182710",
          "title": "Semporna Di Kaki Langit",
          "programmeId": null,
          "episodeId": null,
          "datetime": "2021-01-31 11:30:00.0",
          "datetimeInUtc": "2021-01-31 03:30:00.0",
          "duration": "00:30:00",
          "siTrafficKey": "1:1028:42903939",
          "detailUrl": "/details/Semporna-Di-Kaki-Langit-1:1028:42903939"
        },
        {
          "eventId": "36182711",
          "title": "Visi Intelek",
          "programmeId": null,
          "episodeId": null,
          "datetime": "2021-01-31 12:00:00.0",
          "datetimeInUtc": "2021-01-31 04:00:00.0",
          "duration": "00:30:00",
          "siTrafficKey": "1:1028:42903940",
          "detailUrl": "/details/Visi-Intelek-1:1028:42903940"
        },
        {
          "eventId": "36182712",
          "title": "Ekspresi Muzikku",
          "programmeId": null,
          "episodeId": null,
          "datetime": "2021-01-31 12:30:00.0",
          "datetimeInUtc": "2021-01-31 04:30:00.0",
          "duration": "00:30:00",
          "siTrafficKey": "1:1028:42903941",
          "detailUrl": "/details/Ekspresi-Muzikku-1:1028:42903941"
        },
        {
          "eventId": "36031900",
          "title": "Berita Tengah Hari",
          "programmeId": null,
          "episodeId": null,
          "datetime": "2021-01-31 13:00:00.0",
          "datetimeInUtc": "2021-01-31 05:00:00.0",
          "duration": "00:30:00",
          "siTrafficKey": "1:1028:42612383",
          "detailUrl": "/details/Berita-Tengah-Hari-1:1028:42612383"
        },
        {
          "eventId": "36182713",
          "title": "Singgah Di Agro",
          "programmeId": null,
          "episodeId": null,
          "datetime": "2021-01-31 13:30:00.0",
          "datetimeInUtc": "2021-01-31 05:30:00.0",
          "duration": "00:30:00",
          "siTrafficKey": "1:1028:42903942",
          "detailUrl": "/details/Singgah-Di-Agro-1:1028:42903942"
        },
        {
          "eventId": "36182714",
          "title": "Wira Remaja",
          "programmeId": null,
          "episodeId": null,
          "datetime": "2021-01-31 14:00:00.0",
          "datetimeInUtc": "2021-01-31 06:00:00.0",
          "duration": "01:00:00",
          "siTrafficKey": "1:1028:42903943",
          "detailUrl": "/details/Wira-Remaja-1:1028:42903943"
        },
        {
          "eventId": "36031903",
          "title": "Teristimewa",
          "programmeId": null,
          "episodeId": null,
          "datetime": "2021-01-31 15:00:00.0",
          "datetimeInUtc": "2021-01-31 07:00:00.0",
          "duration": "01:00:00",
          "siTrafficKey": "1:1028:42612386",
          "detailUrl": "/details/Teristimewa-1:1028:42612386"
        },
        {
          "eventId": "36182715",
          "title": "Pesona Malaysia",
          "programmeId": null,
          "episodeId": null,
          "datetime": "2021-01-31 16:00:00.0",
          "datetimeInUtc": "2021-01-31 08:00:00.0",
          "duration": "01:00:00",
          "siTrafficKey": "1:1028:42903944",
          "detailUrl": "/details/Pesona-Malaysia-1:1028:42903944"
        },
        {
          "eventId": "36031905",
          "title": "Berita Wilayah",
          "programmeId": null,
          "episodeId": null,
          "datetime": "2021-01-31 17:00:00.0",
          "datetimeInUtc": "2021-01-31 09:00:00.0",
          "duration": "01:00:00",
          "siTrafficKey": "1:1028:42612388",
          "detailUrl": "/details/Berita-Wilayah-1:1028:42612388"
        },
        {
          "eventId": "36031906",
          "title": "Semalam Di Malaysia",
          "programmeId": null,
          "episodeId": null,
          "datetime": "2021-01-31 18:00:00.0",
          "datetimeInUtc": "2021-01-31 10:00:00.0",
          "duration": "00:30:00",
          "siTrafficKey": "1:1028:42612389",
          "detailUrl": "/details/Semalam-Di-Malaysia-1:1028:42612389"
        },
        {
          "eventId": "36031907",
          "title": "Persada Jurnal",
          "programmeId": null,
          "episodeId": null,
          "datetime": "2021-01-31 18:30:00.0",
          "datetimeInUtc": "2021-01-31 10:30:00.0",
          "duration": "00:30:00",
          "siTrafficKey": "1:1028:42612390",
          "detailUrl": "/details/Persada-Jurnal-1:1028:42612390"
        },
        {
          "eventId": "36182716",
          "title": "Nota Buat Cempaka",
          "programmeId": null,
          "episodeId": null,
          "datetime": "2021-01-31 19:00:00.0",
          "datetimeInUtc": "2021-01-31 11:00:00.0",
          "duration": "01:00:00",
          "siTrafficKey": "1:1028:42903945",
          "detailUrl": "/details/Nota-Buat-Cempaka-1:1028:42903945"
        },
        {
          "eventId": "36031909",
          "title": "Berita Perdana",
          "programmeId": null,
          "episodeId": null,
          "datetime": "2021-01-31 20:00:00.0",
          "datetimeInUtc": "2021-01-31 12:00:00.0",
          "duration": "01:00:00",
          "siTrafficKey": "1:1028:42612392",
          "detailUrl": "/details/Berita-Perdana-1:1028:42612392"
        },
        {
          "eventId": "36182717",
          "title": "Istimewa Legen",
          "programmeId": null,
          "episodeId": null,
          "datetime": "2021-01-31 21:00:00.0",
          "datetimeInUtc": "2021-01-31 13:00:00.0",
          "duration": "01:30:00",
          "siTrafficKey": "1:1028:42903946",
          "detailUrl": "/details/Istimewa-Legen-1:1028:42903946"
        },
        {
          "eventId": "36182718",
          "title": "Sukan Lejen - Diskusi Imbasan",
          "programmeId": null,
          "episodeId": null,
          "datetime": "2021-01-31 22:30:00.0",
          "datetimeInUtc": "2021-01-31 14:30:00.0",
          "duration": "01:00:00",
          "siTrafficKey": "1:1028:42903947",
          "detailUrl": "/details/Sukan-Lejen-Diskusi-Imbasan-1:1028:42903947"
        },
        {
          "eventId": "36182719",
          "title": "Semporna Di Kaki Langit",
          "programmeId": null,
          "episodeId": null,
          "datetime": "2021-01-31 23:30:00.0",
          "datetimeInUtc": "2021-01-31 15:30:00.0",
          "duration": "00:30:00",
          "siTrafficKey": "1:1028:42903948",
          "detailUrl": "/details/Semporna-Di-Kaki-Langit-1:1028:42903948"
        }
      ],
      "2021-02-01": [
        {
          "eventId": "36182720",
          "title": "Berita Tengah Malam",
          "programmeId": null,
          "episodeId": null,
          "datetime": "2021-02-01 00:00:00.0",
          "datetimeInUtc": "2021-01-31 16:00:00.0",
          "duration": "00:30:00",
          "siTrafficKey": "1:1028:42823227",
          "detailUrl": "/details/Berita-Tengah-Malam-1:1028:42823227"
        },
        {
          "eventId": "36182721",
          "title": "Trans World Sports",
          "programmeId": null,
          "episodeId": null,
          "datetime": "2021-02-01 00:30:00.0",
          "datetimeInUtc": "2021-01-31 16:30:00.0",
          "duration": "01:00:00",
          "siTrafficKey": "1:1028:42903949",
          "detailUrl": "/details/Trans-World-Sports-1:1028:42903949"
        },
        {
          "eventId": "36182722",
          "title": "Teristimewa",
          "programmeId": null,
          "episodeId": null,
          "datetime": "2021-02-01 01:30:00.0",
          "datetimeInUtc": "2021-01-31 17:30:00.0",
          "duration": "01:00:00",
          "siTrafficKey": "1:1028:42903950",
          "detailUrl": "/details/Teristimewa-1:1028:42903950"
        },
        {
          "eventId": "36182723",
          "title": "Pesona Malaysia",
          "programmeId": null,
          "episodeId": null,
          "datetime": "2021-02-01 02:30:00.0",
          "datetimeInUtc": "2021-01-31 18:30:00.0",
          "duration": "01:00:00",
          "siTrafficKey": "1:1028:42903951",
          "detailUrl": "/details/Pesona-Malaysia-1:1028:42903951"
        },
        {
          "eventId": "36182724",
          "title": "Ekspresi Muzikku",
          "programmeId": null,
          "episodeId": null,
          "datetime": "2021-02-01 03:30:00.0",
          "datetimeInUtc": "2021-01-31 19:30:00.0",
          "duration": "00:30:00",
          "siTrafficKey": "1:1028:42903952",
          "detailUrl": "/details/Ekspresi-Muzikku-1:1028:42903952"
        },
        {
          "eventId": "36182725",
          "title": "Usung Putih",
          "programmeId": null,
          "episodeId": null,
          "datetime": "2021-02-01 04:00:00.0",
          "datetimeInUtc": "2021-01-31 20:00:00.0",
          "duration": "02:00:00",
          "siTrafficKey": "1:1028:42903953",
          "detailUrl": "/details/Usung-Putih-1:1028:42903953"
        },
        {
          "eventId": "36196120",
          "title": "Kembara Damai",
          "programmeId": null,
          "episodeId": null,
          "datetime": "2021-02-01 06:00:00.0",
          "datetimeInUtc": "2021-01-31 22:00:00.0",
          "duration": "00:30:00",
          "siTrafficKey": "1:1028:42961027",
          "detailUrl": "/details/Kembara-Damai-1:1028:42961027"
        },
        {
          "eventId": "36196121",
          "title": "Muqaddam",
          "programmeId": null,
          "episodeId": null,
          "datetime": "2021-02-01 06:30:00.0",
          "datetimeInUtc": "2021-01-31 22:30:00.0",
          "duration": "00:30:00",
          "siTrafficKey": "1:1028:42961028",
          "detailUrl": "/details/Muqaddam-1:1028:42961028"
        },
        {
          "eventId": "36196122",
          "title": "Berita Pagi",
          "programmeId": null,
          "episodeId": null,
          "datetime": "2021-02-01 07:00:00.0",
          "datetimeInUtc": "2021-01-31 23:00:00.0",
          "duration": "00:30:00",
          "siTrafficKey": "1:1028:42961029",
          "detailUrl": "/details/Berita-Pagi-1:1028:42961029"
        },
        {
          "eventId": "36196123",
          "title": "Berita Pagi Sabah",
          "programmeId": null,
          "episodeId": null,
          "datetime": "2021-02-01 07:30:00.0",
          "datetimeInUtc": "2021-01-31 23:30:00.0",
          "duration": "00:15:00",
          "siTrafficKey": "1:1028:42961030",
          "detailUrl": "/details/Berita-Pagi-Sabah-1:1028:42961030"
        },
        {
          "eventId": "36196124",
          "title": "Berita Pagi Sarawak",
          "programmeId": null,
          "episodeId": null,
          "datetime": "2021-02-01 07:45:00.0",
          "datetimeInUtc": "2021-01-31 23:45:00.0",
          "duration": "00:15:00",
          "siTrafficKey": "1:1028:42961031",
          "detailUrl": "/details/Berita-Pagi-Sarawak-1:1028:42961031"
        },
        {
          "eventId": "36196125",
          "title": "(L) Selamat Pagi Malaysia",
          "programmeId": null,
          "episodeId": null,
          "datetime": "2021-02-01 08:00:00.0",
          "datetimeInUtc": "2021-02-01 00:00:00.0",
          "duration": "02:00:00",
          "siTrafficKey": "1:1028:42961032",
          "detailUrl": "/details/L-Selamat-Pagi-Malaysia-1:1028:42961032"
        },
        {
          "eventId": "36196126",
          "title": "Busana Adat",
          "programmeId": null,
          "episodeId": null,
          "datetime": "2021-02-01 10:00:00.0",
          "datetimeInUtc": "2021-02-01 02:00:00.0",
          "duration": "00:30:00",
          "siTrafficKey": "1:1028:42961033",
          "detailUrl": "/details/Busana-Adat-1:1028:42961033"
        },
        {
          "eventId": "36196127",
          "title": "Gadis Dan Gua",
          "programmeId": null,
          "episodeId": null,
          "datetime": "2021-02-01 10:30:00.0",
          "datetimeInUtc": "2021-02-01 02:30:00.0",
          "duration": "00:30:00",
          "siTrafficKey": "1:1028:42961034",
          "detailUrl": "/details/Gadis-Dan-Gua-1:1028:42961034"
        },
        {
          "eventId": "36196128",
          "title": "Citarasa Medika",
          "programmeId": null,
          "episodeId": null,
          "datetime": "2021-02-01 11:00:00.0",
          "datetimeInUtc": "2021-02-01 03:00:00.0",
          "duration": "00:30:00",
          "siTrafficKey": "1:1028:42961035",
          "detailUrl": "/details/Citarasa-Medika-1:1028:42961035"
        },
        {
          "eventId": "36196129",
          "title": "Jom Kayuh",
          "programmeId": null,
          "episodeId": null,
          "datetime": "2021-02-01 11:30:00.0",
          "datetimeInUtc": "2021-02-01 03:30:00.0",
          "duration": "00:30:00",
          "siTrafficKey": "1:1028:42961036",
          "detailUrl": "/details/Jom-Kayuh-1:1028:42961036"
        },
        {
          "eventId": "36196130",
          "title": "Great Blue Wild",
          "programmeId": null,
          "episodeId": null,
          "datetime": "2021-02-01 12:00:00.0",
          "datetimeInUtc": "2021-02-01 04:00:00.0",
          "duration": "01:00:00",
          "siTrafficKey": "1:1028:42961037",
          "detailUrl": "/details/Great-Blue-Wild-1:1028:42961037"
        },
        {
          "eventId": "36196131",
          "title": "Berita Tengah Hari",
          "programmeId": null,
          "episodeId": null,
          "datetime": "2021-02-01 13:00:00.0",
          "datetimeInUtc": "2021-02-01 05:00:00.0",
          "duration": "00:30:00",
          "siTrafficKey": "1:1028:42961038",
          "detailUrl": "/details/Berita-Tengah-Hari-1:1028:42961038"
        },
        {
          "eventId": "36196132",
          "title": "Ekspresi Eko",
          "programmeId": null,
          "episodeId": null,
          "datetime": "2021-02-01 13:30:00.0",
          "datetimeInUtc": "2021-02-01 05:30:00.0",
          "duration": "00:30:00",
          "siTrafficKey": "1:1028:42961039",
          "detailUrl": "/details/Ekspresi-Eko-1:1028:42961039"
        },
        {
          "eventId": "36196133",
          "title": "Monograf Seni Bina Malaysia",
          "programmeId": null,
          "episodeId": null,
          "datetime": "2021-02-01 14:00:00.0",
          "datetimeInUtc": "2021-02-01 06:00:00.0",
          "duration": "01:00:00",
          "siTrafficKey": "1:1028:42961040",
          "detailUrl": "/details/Monograf-Seni-Bina-Malaysia-1:1028:42961040"
        },
        {
          "eventId": "36196134",
          "title": "Nana Nini Nunu",
          "programmeId": null,
          "episodeId": null,
          "datetime": "2021-02-01 15:00:00.0",
          "datetimeInUtc": "2021-02-01 07:00:00.0",
          "duration": "01:00:00",
          "siTrafficKey": "1:1028:42961041",
          "detailUrl": "/details/Nana-Nini-Nunu-1:1028:42961041"
        },
        {
          "eventId": "36196135",
          "title": "Kembara Khatulistiwa",
          "programmeId": null,
          "episodeId": null,
          "datetime": "2021-02-01 16:00:00.0",
          "datetimeInUtc": "2021-02-01 08:00:00.0",
          "duration": "00:30:00",
          "siTrafficKey": "1:1028:42961042",
          "detailUrl": "/details/Kembara-Khatulistiwa-1:1028:42961042"
        },
        {
          "eventId": "36196136",
          "title": "Not Available",
          "programmeId": null,
          "episodeId": null,
          "datetime": "2021-02-01 16:30:00.0",
          "datetimeInUtc": "2021-02-01 08:30:00.0",
          "duration": "00:30:00",
          "siTrafficKey": "1:1028:42961043",
          "detailUrl": "/details/Not-Available-1:1028:42961043"
        },
        {
          "eventId": "36196137",
          "title": "Berita Wilayah",
          "programmeId": null,
          "episodeId": null,
          "datetime": "2021-02-01 17:00:00.0",
          "datetimeInUtc": "2021-02-01 09:00:00.0",
          "duration": "01:00:00",
          "siTrafficKey": "1:1028:42961044",
          "detailUrl": "/details/Berita-Wilayah-1:1028:42961044"
        },
        {
          "eventId": "36196138",
          "title": "Santai Rider",
          "programmeId": null,
          "episodeId": null,
          "datetime": "2021-02-01 18:00:00.0",
          "datetimeInUtc": "2021-02-01 10:00:00.0",
          "duration": "00:30:00",
          "siTrafficKey": "1:1028:42961045",
          "detailUrl": "/details/Santai-Rider-1:1028:42961045"
        },
        {
          "eventId": "36196139",
          "title": "Pewaris Legasi",
          "programmeId": null,
          "episodeId": null,
          "datetime": "2021-02-01 18:30:00.0",
          "datetimeInUtc": "2021-02-01 10:30:00.0",
          "duration": "00:30:00",
          "siTrafficKey": "1:1028:42961046",
          "detailUrl": "/details/Pewaris-Legasi-1:1028:42961046"
        },
        {
          "eventId": "36196140",
          "title": "Mimpi Yang Sempurna",
          "programmeId": null,
          "episodeId": null,
          "datetime": "2021-02-01 19:00:00.0",
          "datetimeInUtc": "2021-02-01 11:00:00.0",
          "duration": "01:00:00",
          "siTrafficKey": "1:1028:42961047",
          "detailUrl": "/details/Mimpi-Yang-Sempurna-1:1028:42961047"
        },
        {
          "eventId": "36196141",
          "title": "Berita Perdana",
          "programmeId": null,
          "episodeId": null,
          "datetime": "2021-02-01 20:00:00.0",
          "datetimeInUtc": "2021-02-01 12:00:00.0",
          "duration": "01:00:00",
          "siTrafficKey": "1:1028:42961048",
          "detailUrl": "/details/Berita-Perdana-1:1028:42961048"
        },
        {
          "eventId": "36196142",
          "title": "(L) Bicara Pengguna",
          "programmeId": null,
          "episodeId": null,
          "datetime": "2021-02-01 21:00:00.0",
          "datetimeInUtc": "2021-02-01 13:00:00.0",
          "duration": "01:00:00",
          "siTrafficKey": "1:1028:42961049",
          "detailUrl": "/details/L-Bicara-Pengguna-1:1028:42961049"
        },
        {
          "eventId": "36196143",
          "title": "Panorama",
          "programmeId": null,
          "episodeId": null,
          "datetime": "2021-02-01 22:00:00.0",
          "datetimeInUtc": "2021-02-01 14:00:00.0",
          "duration": "00:30:00",
          "siTrafficKey": "1:1028:42961050",
          "detailUrl": "/details/Panorama-1:1028:42961050"
        },
        {
          "eventId": "36196144",
          "title": "Buaian Kasih",
          "programmeId": null,
          "episodeId": null,
          "datetime": "2021-02-01 22:30:00.0",
          "datetimeInUtc": "2021-02-01 14:30:00.0",
          "duration": "00:30:00",
          "siTrafficKey": "1:1028:42961051",
          "detailUrl": "/details/Buaian-Kasih-1:1028:42961051"
        },
        {
          "eventId": "36196145",
          "title": "Berita Dunia",
          "programmeId": null,
          "episodeId": null,
          "datetime": "2021-02-01 23:00:00.0",
          "datetimeInUtc": "2021-02-01 15:00:00.0",
          "duration": "00:30:00",
          "siTrafficKey": "1:1028:42961052",
          "detailUrl": "/details/Berita-Dunia-1:1028:42961052"
        },
        {
          "eventId": "36196146",
          "title": "Sukan",
          "programmeId": null,
          "episodeId": null,
          "datetime": "2021-02-01 23:30:00.0",
          "datetimeInUtc": "2021-02-01 15:30:00.0",
          "duration": "00:30:00",
          "siTrafficKey": "1:1028:42961053",
          "detailUrl": "/details/Sukan-1:1028:42961053"
        }
      ],
      "2021-02-02": [
        {
          "eventId": "36196147",
          "title": "Berita Tengah Malam",
          "programmeId": null,
          "episodeId": null,
          "datetime": "2021-02-02 00:00:00.0",
          "datetimeInUtc": "2021-02-01 16:00:00.0",
          "duration": "00:30:00",
          "siTrafficKey": "1:1028:42961054",
          "detailUrl": "/details/Berita-Tengah-Malam-1:1028:42961054"
        },
        {
          "eventId": "36196148",
          "title": "Trans World Sports",
          "programmeId": null,
          "episodeId": null,
          "datetime": "2021-02-02 00:30:00.0",
          "datetimeInUtc": "2021-02-01 16:30:00.0",
          "duration": "01:00:00",
          "siTrafficKey": "1:1028:42961055",
          "detailUrl": "/details/Trans-World-Sports-1:1028:42961055"
        },
        {
          "eventId": "36196149",
          "title": "Busana Adat",
          "programmeId": null,
          "episodeId": null,
          "datetime": "2021-02-02 01:30:00.0",
          "datetimeInUtc": "2021-02-01 17:30:00.0",
          "duration": "00:30:00",
          "siTrafficKey": "1:1028:42961056",
          "detailUrl": "/details/Busana-Adat-1:1028:42961056"
        },
        {
          "eventId": "36196150",
          "title": "Citarasa Medika",
          "programmeId": null,
          "episodeId": null,
          "datetime": "2021-02-02 02:00:00.0",
          "datetimeInUtc": "2021-02-01 18:00:00.0",
          "duration": "00:30:00",
          "siTrafficKey": "1:1028:42961057",
          "detailUrl": "/details/Citarasa-Medika-1:1028:42961057"
        },
        {
          "eventId": "36196151",
          "title": "Ekspresi Eko",
          "programmeId": null,
          "episodeId": null,
          "datetime": "2021-02-02 02:30:00.0",
          "datetimeInUtc": "2021-02-01 18:30:00.0",
          "duration": "00:30:00",
          "siTrafficKey": "1:1028:42961058",
          "detailUrl": "/details/Ekspresi-Eko-1:1028:42961058"
        },
        {
          "eventId": "36196152",
          "title": "Kembara Damai",
          "programmeId": null,
          "episodeId": null,
          "datetime": "2021-02-02 03:00:00.0",
          "datetimeInUtc": "2021-02-01 19:00:00.0",
          "duration": "00:30:00",
          "siTrafficKey": "1:1028:42961059",
          "detailUrl": "/details/Kembara-Damai-1:1028:42961059"
        },
        {
          "eventId": "36196153",
          "title": "Dari Mata Arisa",
          "programmeId": null,
          "episodeId": null,
          "datetime": "2021-02-02 03:30:00.0",
          "datetimeInUtc": "2021-02-01 19:30:00.0",
          "duration": "01:00:00",
          "siTrafficKey": "1:1028:42961060",
          "detailUrl": "/details/Dari-Mata-Arisa-1:1028:42961060"
        },
        {
          "eventId": "36196154",
          "title": "Jom Kayuh",
          "programmeId": null,
          "episodeId": null,
          "datetime": "2021-02-02 04:30:00.0",
          "datetimeInUtc": "2021-02-01 20:30:00.0",
          "duration": "00:30:00",
          "siTrafficKey": "1:1028:42961061",
          "detailUrl": "/details/Jom-Kayuh-1:1028:42961061"
        },
        {
          "eventId": "36196155",
          "title": "Nana Nini Nunu",
          "programmeId": null,
          "episodeId": null,
          "datetime": "2021-02-02 05:00:00.0",
          "datetimeInUtc": "2021-02-01 21:00:00.0",
          "duration": "01:00:00",
          "siTrafficKey": "1:1028:42961062",
          "detailUrl": "/details/Nana-Nini-Nunu-1:1028:42961062"
        },
        {
          "eventId": "36196156",
          "title": "Kembara Damai",
          "programmeId": null,
          "episodeId": null,
          "datetime": "2021-02-02 06:00:00.0",
          "datetimeInUtc": "2021-02-01 22:00:00.0",
          "duration": "00:30:00",
          "siTrafficKey": "1:1028:42961063",
          "detailUrl": "/details/Kembara-Damai-1:1028:42961063"
        },
        {
          "eventId": "36196157",
          "title": "Persada Jurnal",
          "programmeId": null,
          "episodeId": null,
          "datetime": "2021-02-02 06:30:00.0",
          "datetimeInUtc": "2021-02-01 22:30:00.0",
          "duration": "00:30:00",
          "siTrafficKey": "1:1028:42961064",
          "detailUrl": "/details/Persada-Jurnal-1:1028:42961064"
        },
        {
          "eventId": "36196158",
          "title": "Berita Pagi",
          "programmeId": null,
          "episodeId": null,
          "datetime": "2021-02-02 07:00:00.0",
          "datetimeInUtc": "2021-02-01 23:00:00.0",
          "duration": "00:30:00",
          "siTrafficKey": "1:1028:42961065",
          "detailUrl": "/details/Berita-Pagi-1:1028:42961065"
        },
        {
          "eventId": "36196159",
          "title": "Berita Pagi Sabah",
          "programmeId": null,
          "episodeId": null,
          "datetime": "2021-02-02 07:30:00.0",
          "datetimeInUtc": "2021-02-01 23:30:00.0",
          "duration": "00:15:00",
          "siTrafficKey": "1:1028:42961066",
          "detailUrl": "/details/Berita-Pagi-Sabah-1:1028:42961066"
        },
        {
          "eventId": "36196160",
          "title": "Berita Pagi Sarawak",
          "programmeId": null,
          "episodeId": null,
          "datetime": "2021-02-02 07:45:00.0",
          "datetimeInUtc": "2021-02-01 23:45:00.0",
          "duration": "00:15:00",
          "siTrafficKey": "1:1028:42961067",
          "detailUrl": "/details/Berita-Pagi-Sarawak-1:1028:42961067"
        },
        {
          "eventId": "36196161",
          "title": "(L) Selamat Pagi Malaysia",
          "programmeId": null,
          "episodeId": null,
          "datetime": "2021-02-02 08:00:00.0",
          "datetimeInUtc": "2021-02-02 00:00:00.0",
          "duration": "02:00:00",
          "siTrafficKey": "1:1028:42961068",
          "detailUrl": "/details/L-Selamat-Pagi-Malaysia-1:1028:42961068"
        },
        {
          "eventId": "36223477",
          "title": "Busana Adat",
          "programmeId": null,
          "episodeId": null,
          "datetime": "2021-02-02 10:00:00.0",
          "datetimeInUtc": "2021-02-02 02:00:00.0",
          "duration": "00:30:00",
          "siTrafficKey": "1:1028:42989994",
          "detailUrl": "/details/Busana-Adat-1:1028:42989994"
        },
        {
          "eventId": "36223478",
          "title": "Gadis Dan Gua",
          "programmeId": null,
          "episodeId": null,
          "datetime": "2021-02-02 10:30:00.0",
          "datetimeInUtc": "2021-02-02 02:30:00.0",
          "duration": "00:30:00",
          "siTrafficKey": "1:1028:42989995",
          "detailUrl": "/details/Gadis-Dan-Gua-1:1028:42989995"
        },
        {
          "eventId": "36223479",
          "title": "Citarasa Medika",
          "programmeId": null,
          "episodeId": null,
          "datetime": "2021-02-02 11:00:00.0",
          "datetimeInUtc": "2021-02-02 03:00:00.0",
          "duration": "00:30:00",
          "siTrafficKey": "1:1028:42989996",
          "detailUrl": "/details/Citarasa-Medika-1:1028:42989996"
        },
        {
          "eventId": "36223480",
          "title": "Jom Kayuh",
          "programmeId": null,
          "episodeId": null,
          "datetime": "2021-02-02 11:30:00.0",
          "datetimeInUtc": "2021-02-02 03:30:00.0",
          "duration": "00:30:00",
          "siTrafficKey": "1:1028:42989997",
          "detailUrl": "/details/Jom-Kayuh-1:1028:42989997"
        },
        {
          "eventId": "36223481",
          "title": "Great Blue Wild",
          "programmeId": null,
          "episodeId": null,
          "datetime": "2021-02-02 12:00:00.0",
          "datetimeInUtc": "2021-02-02 04:00:00.0",
          "duration": "01:00:00",
          "siTrafficKey": "1:1028:42989998",
          "detailUrl": "/details/Great-Blue-Wild-1:1028:42989998"
        },
        {
          "eventId": "36196167",
          "title": "Berita Tengah Hari",
          "programmeId": null,
          "episodeId": null,
          "datetime": "2021-02-02 13:00:00.0",
          "datetimeInUtc": "2021-02-02 05:00:00.0",
          "duration": "00:30:00",
          "siTrafficKey": "1:1028:42961074",
          "detailUrl": "/details/Berita-Tengah-Hari-1:1028:42961074"
        },
        {
          "eventId": "36223482",
          "title": "Kota Warisan Alam",
          "programmeId": null,
          "episodeId": null,
          "datetime": "2021-02-02 13:30:00.0",
          "datetimeInUtc": "2021-02-02 05:30:00.0",
          "duration": "00:30:00",
          "siTrafficKey": "1:1028:42989999",
          "detailUrl": "/details/Kota-Warisan-Alam-1:1028:42989999"
        },
        {
          "eventId": "36196169",
          "title": "Kuppa Kopi",
          "programmeId": null,
          "episodeId": null,
          "datetime": "2021-02-02 14:00:00.0",
          "datetimeInUtc": "2021-02-02 06:00:00.0",
          "duration": "01:00:00",
          "siTrafficKey": "1:1028:42961076",
          "detailUrl": "/details/Kuppa-Kopi-1:1028:42961076"
        },
        {
          "eventId": "36223483",
          "title": "Mahligai Kaca",
          "programmeId": null,
          "episodeId": null,
          "datetime": "2021-02-02 15:00:00.0",
          "datetimeInUtc": "2021-02-02 07:00:00.0",
          "duration": "01:00:00",
          "siTrafficKey": "1:1028:42990000",
          "detailUrl": "/details/Mahligai-Kaca-1:1028:42990000"
        },
        {
          "eventId": "36196171",
          "title": "Kembara Khatulistiwa",
          "programmeId": null,
          "episodeId": null,
          "datetime": "2021-02-02 16:00:00.0",
          "datetimeInUtc": "2021-02-02 08:00:00.0",
          "duration": "00:30:00",
          "siTrafficKey": "1:1028:42961078",
          "detailUrl": "/details/Kembara-Khatulistiwa-1:1028:42961078"
        },
        {
          "eventId": "36196172",
          "title": "Not Available",
          "programmeId": null,
          "episodeId": null,
          "datetime": "2021-02-02 16:30:00.0",
          "datetimeInUtc": "2021-02-02 08:30:00.0",
          "duration": "00:30:00",
          "siTrafficKey": "1:1028:42961079",
          "detailUrl": "/details/Not-Available-1:1028:42961079"
        },
        {
          "eventId": "36196173",
          "title": "Berita Wilayah",
          "programmeId": null,
          "episodeId": null,
          "datetime": "2021-02-02 17:00:00.0",
          "datetimeInUtc": "2021-02-02 09:00:00.0",
          "duration": "01:00:00",
          "siTrafficKey": "1:1028:42961080",
          "detailUrl": "/details/Berita-Wilayah-1:1028:42961080"
        },
        {
          "eventId": "36196174",
          "title": "Fikrah",
          "programmeId": null,
          "episodeId": null,
          "datetime": "2021-02-02 18:00:00.0",
          "datetimeInUtc": "2021-02-02 10:00:00.0",
          "duration": "01:00:00",
          "siTrafficKey": "1:1028:42961081",
          "detailUrl": "/details/Fikrah-1:1028:42961081"
        },
        {
          "eventId": "36223484",
          "title": "Mimpi Yang Sempurna",
          "programmeId": null,
          "episodeId": null,
          "datetime": "2021-02-02 19:00:00.0",
          "datetimeInUtc": "2021-02-02 11:00:00.0",
          "duration": "01:00:00",
          "siTrafficKey": "1:1028:42990001",
          "detailUrl": "/details/Mimpi-Yang-Sempurna-1:1028:42990001"
        },
        {
          "eventId": "36196176",
          "title": "Berita Perdana",
          "programmeId": null,
          "episodeId": null,
          "datetime": "2021-02-02 20:00:00.0",
          "datetimeInUtc": "2021-02-02 12:00:00.0",
          "duration": "01:00:00",
          "siTrafficKey": "1:1028:42961083",
          "detailUrl": "/details/Berita-Perdana-1:1028:42961083"
        },
        {
          "eventId": "36196177",
          "title": "(L) Bicara Inspirasi",
          "programmeId": null,
          "episodeId": null,
          "datetime": "2021-02-02 21:00:00.0",
          "datetimeInUtc": "2021-02-02 13:00:00.0",
          "duration": "01:00:00",
          "siTrafficKey": "1:1028:42961084",
          "detailUrl": "/details/L-Bicara-Inspirasi-1:1028:42961084"
        },
        {
          "eventId": "36196178",
          "title": "Simfoni Alam",
          "programmeId": null,
          "episodeId": null,
          "datetime": "2021-02-02 22:00:00.0",
          "datetimeInUtc": "2021-02-02 14:00:00.0",
          "duration": "00:30:00",
          "siTrafficKey": "1:1028:42961085",
          "detailUrl": "/details/Simfoni-Alam-1:1028:42961085"
        },
        {
          "eventId": "36223485",
          "title": "Buaian Kasih",
          "programmeId": null,
          "episodeId": null,
          "datetime": "2021-02-02 22:30:00.0",
          "datetimeInUtc": "2021-02-02 14:30:00.0",
          "duration": "00:30:00",
          "siTrafficKey": "1:1028:42990002",
          "detailUrl": "/details/Buaian-Kasih-1:1028:42990002"
        },
        {
          "eventId": "36196180",
          "title": "Berita Dunia",
          "programmeId": null,
          "episodeId": null,
          "datetime": "2021-02-02 23:00:00.0",
          "datetimeInUtc": "2021-02-02 15:00:00.0",
          "duration": "00:30:00",
          "siTrafficKey": "1:1028:42961087",
          "detailUrl": "/details/Berita-Dunia-1:1028:42961087"
        },
        {
          "eventId": "36196181",
          "title": "Atp Uncovered",
          "programmeId": null,
          "episodeId": null,
          "datetime": "2021-02-02 23:30:00.0",
          "datetimeInUtc": "2021-02-02 15:30:00.0",
          "duration": "00:30:00",
          "siTrafficKey": "1:1028:42961088",
          "detailUrl": "/details/Atp-Uncovered-1:1028:42961088"
        }
      ],
      "2021-02-03": [
        {
          "eventId": "36196182",
          "title": "Berita Tengah Malam",
          "programmeId": null,
          "episodeId": null,
          "datetime": "2021-02-03 00:00:00.0",
          "datetimeInUtc": "2021-02-02 16:00:00.0",
          "duration": "00:30:00",
          "siTrafficKey": "1:1028:42961089",
          "detailUrl": "/details/Berita-Tengah-Malam-1:1028:42961089"
        },
        {
          "eventId": "36196183",
          "title": "Trans World Sports",
          "programmeId": null,
          "episodeId": null,
          "datetime": "2021-02-03 00:30:00.0",
          "datetimeInUtc": "2021-02-02 16:30:00.0",
          "duration": "01:00:00",
          "siTrafficKey": "1:1028:42961090",
          "detailUrl": "/details/Trans-World-Sports-1:1028:42961090"
        },
        {
          "eventId": "36196184",
          "title": "Busana Adat",
          "programmeId": null,
          "episodeId": null,
          "datetime": "2021-02-03 01:30:00.0",
          "datetimeInUtc": "2021-02-02 17:30:00.0",
          "duration": "00:30:00",
          "siTrafficKey": "1:1028:42961091",
          "detailUrl": "/details/Busana-Adat-1:1028:42961091"
        },
        {
          "eventId": "36196185",
          "title": "Citarasa Medika",
          "programmeId": null,
          "episodeId": null,
          "datetime": "2021-02-03 02:00:00.0",
          "datetimeInUtc": "2021-02-02 18:00:00.0",
          "duration": "00:30:00",
          "siTrafficKey": "1:1028:42961092",
          "detailUrl": "/details/Citarasa-Medika-1:1028:42961092"
        },
        {
          "eventId": "36223486",
          "title": "Kota Warisan Alam",
          "programmeId": null,
          "episodeId": null,
          "datetime": "2021-02-03 02:30:00.0",
          "datetimeInUtc": "2021-02-02 18:30:00.0",
          "duration": "00:30:00",
          "siTrafficKey": "1:1028:42990003",
          "detailUrl": "/details/Kota-Warisan-Alam-1:1028:42990003"
        },
        {
          "eventId": "36196187",
          "title": "Kembara Damai",
          "programmeId": null,
          "episodeId": null,
          "datetime": "2021-02-03 03:00:00.0",
          "datetimeInUtc": "2021-02-02 19:00:00.0",
          "duration": "00:30:00",
          "siTrafficKey": "1:1028:42961094",
          "detailUrl": "/details/Kembara-Damai-1:1028:42961094"
        },
        {
          "eventId": "36196188",
          "title": "Dari Mata Arisa",
          "programmeId": null,
          "episodeId": null,
          "datetime": "2021-02-03 03:30:00.0",
          "datetimeInUtc": "2021-02-02 19:30:00.0",
          "duration": "01:00:00",
          "siTrafficKey": "1:1028:42961095",
          "detailUrl": "/details/Dari-Mata-Arisa-1:1028:42961095"
        },
        {
          "eventId": "36196189",
          "title": "Jom Kayuh",
          "programmeId": null,
          "episodeId": null,
          "datetime": "2021-02-03 04:30:00.0",
          "datetimeInUtc": "2021-02-02 20:30:00.0",
          "duration": "00:30:00",
          "siTrafficKey": "1:1028:42961096",
          "detailUrl": "/details/Jom-Kayuh-1:1028:42961096"
        },
        {
          "eventId": "36223487",
          "title": "Mahligai Kaca",
          "programmeId": null,
          "episodeId": null,
          "datetime": "2021-02-03 05:00:00.0",
          "datetimeInUtc": "2021-02-02 21:00:00.0",
          "duration": "01:00:00",
          "siTrafficKey": "1:1028:42990004",
          "detailUrl": "/details/Mahligai-Kaca-1:1028:42990004"
        },
        {
          "eventId": "36210197",
          "title": "Fikrah",
          "programmeId": null,
          "episodeId": null,
          "datetime": "2021-02-03 06:00:00.0",
          "datetimeInUtc": "2021-02-02 22:00:00.0",
          "duration": "01:00:00",
          "siTrafficKey": "1:1028:42961098",
          "detailUrl": "/details/Fikrah-1:1028:42961098"
        },
        {
          "eventId": "36210198",
          "title": "Berita Pagi",
          "programmeId": null,
          "episodeId": null,
          "datetime": "2021-02-03 07:00:00.0",
          "datetimeInUtc": "2021-02-02 23:00:00.0",
          "duration": "00:30:00",
          "siTrafficKey": "1:1028:42961099",
          "detailUrl": "/details/Berita-Pagi-1:1028:42961099"
        },
        {
          "eventId": "36210199",
          "title": "Berita Pagi Sabah",
          "programmeId": null,
          "episodeId": null,
          "datetime": "2021-02-03 07:30:00.0",
          "datetimeInUtc": "2021-02-02 23:30:00.0",
          "duration": "00:15:00",
          "siTrafficKey": "1:1028:42961100",
          "detailUrl": "/details/Berita-Pagi-Sabah-1:1028:42961100"
        },
        {
          "eventId": "36210200",
          "title": "Berita Pagi Sarawak",
          "programmeId": null,
          "episodeId": null,
          "datetime": "2021-02-03 07:45:00.0",
          "datetimeInUtc": "2021-02-02 23:45:00.0",
          "duration": "00:15:00",
          "siTrafficKey": "1:1028:42961101",
          "detailUrl": "/details/Berita-Pagi-Sarawak-1:1028:42961101"
        },
        {
          "eventId": "36210201",
          "title": "(L) Selamat Pagi Malaysia",
          "programmeId": null,
          "episodeId": null,
          "datetime": "2021-02-03 08:00:00.0",
          "datetimeInUtc": "2021-02-03 00:00:00.0",
          "duration": "02:00:00",
          "siTrafficKey": "1:1028:42961102",
          "detailUrl": "/details/L-Selamat-Pagi-Malaysia-1:1028:42961102"
        },
        {
          "eventId": "36223488",
          "title": "Jiwa Kacau",
          "programmeId": null,
          "episodeId": null,
          "datetime": "2021-02-03 10:00:00.0",
          "datetimeInUtc": "2021-02-03 02:00:00.0",
          "duration": "00:30:00",
          "siTrafficKey": "1:1028:42990005",
          "detailUrl": "/details/Jiwa-Kacau-1:1028:42990005"
        },
        {
          "eventId": "36210203",
          "title": "Nadi Cergas",
          "programmeId": null,
          "episodeId": null,
          "datetime": "2021-02-03 10:30:00.0",
          "datetimeInUtc": "2021-02-03 02:30:00.0",
          "duration": "00:30:00",
          "siTrafficKey": "1:1028:42961104",
          "detailUrl": "/details/Nadi-Cergas-1:1028:42961104"
        },
        {
          "eventId": "36223489",
          "title": "Gelak Sampai Kenyang",
          "programmeId": null,
          "episodeId": null,
          "datetime": "2021-02-03 11:00:00.0",
          "datetimeInUtc": "2021-02-03 03:00:00.0",
          "duration": "00:30:00",
          "siTrafficKey": "1:1028:42990006",
          "detailUrl": "/details/Gelak-Sampai-Kenyang-1:1028:42990006"
        },
        {
          "eventId": "36210205",
          "title": "Klik-Klik",
          "programmeId": null,
          "episodeId": null,
          "datetime": "2021-02-03 11:30:00.0",
          "datetimeInUtc": "2021-02-03 03:30:00.0",
          "duration": "00:30:00",
          "siTrafficKey": "1:1028:42961106",
          "detailUrl": "/details/Klik-Klik-1:1028:42961106"
        },
        {
          "eventId": "36223490",
          "title": "A Year in the Wild",
          "programmeId": null,
          "episodeId": null,
          "datetime": "2021-02-03 12:00:00.0",
          "datetimeInUtc": "2021-02-03 04:00:00.0",
          "duration": "01:00:00",
          "siTrafficKey": "1:1028:42990007",
          "detailUrl": "/details/A-Year-in-the-Wild-1:1028:42990007"
        },
        {
          "eventId": "36210207",
          "title": "Berita Tengah Hari",
          "programmeId": null,
          "episodeId": null,
          "datetime": "2021-02-03 13:00:00.0",
          "datetimeInUtc": "2021-02-03 05:00:00.0",
          "duration": "00:30:00",
          "siTrafficKey": "1:1028:42961108",
          "detailUrl": "/details/Berita-Tengah-Hari-1:1028:42961108"
        },
        {
          "eventId": "36210208",
          "title": "Skuad Chenta",
          "programmeId": null,
          "episodeId": null,
          "datetime": "2021-02-03 13:30:00.0",
          "datetimeInUtc": "2021-02-03 05:30:00.0",
          "duration": "00:30:00",
          "siTrafficKey": "1:1028:42961109",
          "detailUrl": "/details/Skuad-Chenta-1:1028:42961109"
        },
        {
          "eventId": "36210209",
          "title": "My Halal",
          "programmeId": null,
          "episodeId": null,
          "datetime": "2021-02-03 14:00:00.0",
          "datetimeInUtc": "2021-02-03 06:00:00.0",
          "duration": "01:00:00",
          "siTrafficKey": "1:1028:42961110",
          "detailUrl": "/details/My-Halal-1:1028:42961110"
        },
        {
          "eventId": "36223491",
          "title": "Mahligai Kaca",
          "programmeId": null,
          "episodeId": null,
          "datetime": "2021-02-03 15:00:00.0",
          "datetimeInUtc": "2021-02-03 07:00:00.0",
          "duration": "01:00:00",
          "siTrafficKey": "1:1028:42990008",
          "detailUrl": "/details/Mahligai-Kaca-1:1028:42990008"
        },
        {
          "eventId": "36210211",
          "title": "Sinei Kitak Tok",
          "programmeId": null,
          "episodeId": null,
          "datetime": "2021-02-03 16:00:00.0",
          "datetimeInUtc": "2021-02-03 08:00:00.0",
          "duration": "00:30:00",
          "siTrafficKey": "1:1028:42961112",
          "detailUrl": "/details/Sinei-Kitak-Tok-1:1028:42961112"
        },
        {
          "eventId": "36210212",
          "title": "Panorama",
          "programmeId": null,
          "episodeId": null,
          "datetime": "2021-02-03 16:30:00.0",
          "datetimeInUtc": "2021-02-03 08:30:00.0",
          "duration": "00:30:00",
          "siTrafficKey": "1:1028:42961113",
          "detailUrl": "/details/Panorama-1:1028:42961113"
        },
        {
          "eventId": "36210213",
          "title": "Berita Wilayah",
          "programmeId": null,
          "episodeId": null,
          "datetime": "2021-02-03 17:00:00.0",
          "datetimeInUtc": "2021-02-03 09:00:00.0",
          "duration": "01:00:00",
          "siTrafficKey": "1:1028:42961114",
          "detailUrl": "/details/Berita-Wilayah-1:1028:42961114"
        },
        {
          "eventId": "36223492",
          "title": "Bakul Telur Emas",
          "programmeId": null,
          "episodeId": null,
          "datetime": "2021-02-03 18:00:00.0",
          "datetimeInUtc": "2021-02-03 10:00:00.0",
          "duration": "00:30:00",
          "siTrafficKey": "1:1028:42990009",
          "detailUrl": "/details/Bakul-Telur-Emas-1:1028:42990009"
        },
        {
          "eventId": "36223493",
          "title": "Pewaris Legasi",
          "programmeId": null,
          "episodeId": null,
          "datetime": "2021-02-03 18:30:00.0",
          "datetimeInUtc": "2021-02-03 10:30:00.0",
          "duration": "00:30:00",
          "siTrafficKey": "1:1028:42990010",
          "detailUrl": "/details/Pewaris-Legasi-1:1028:42990010"
        },
        {
          "eventId": "36223494",
          "title": "Mimpi Yang Sempurna",
          "programmeId": null,
          "episodeId": null,
          "datetime": "2021-02-03 19:00:00.0",
          "datetimeInUtc": "2021-02-03 11:00:00.0",
          "duration": "01:00:00",
          "siTrafficKey": "1:1028:42990011",
          "detailUrl": "/details/Mimpi-Yang-Sempurna-1:1028:42990011"
        },
        {
          "eventId": "36210217",
          "title": "Berita Perdana",
          "programmeId": null,
          "episodeId": null,
          "datetime": "2021-02-03 20:00:00.0",
          "datetimeInUtc": "2021-02-03 12:00:00.0",
          "duration": "01:00:00",
          "siTrafficKey": "1:1028:42961118",
          "detailUrl": "/details/Berita-Perdana-1:1028:42961118"
        },
        {
          "eventId": "36223495",
          "title": "Bicara Politikonomi",
          "programmeId": null,
          "episodeId": null,
          "datetime": "2021-02-03 21:00:00.0",
          "datetimeInUtc": "2021-02-03 13:00:00.0",
          "duration": "01:00:00",
          "siTrafficKey": "1:1028:42990012",
          "detailUrl": "/details/Bicara-Politikonomi-1:1028:42990012"
        },
        {
          "eventId": "36210219",
          "title": "Rona Sabah",
          "programmeId": null,
          "episodeId": null,
          "datetime": "2021-02-03 22:00:00.0",
          "datetimeInUtc": "2021-02-03 14:00:00.0",
          "duration": "00:30:00",
          "siTrafficKey": "1:1028:42961120",
          "detailUrl": "/details/Rona-Sabah-1:1028:42961120"
        },
        {
          "eventId": "36210220",
          "title": "Buaian Kasih",
          "programmeId": null,
          "episodeId": null,
          "datetime": "2021-02-03 22:30:00.0",
          "datetimeInUtc": "2021-02-03 14:30:00.0",
          "duration": "00:30:00",
          "siTrafficKey": "1:1028:42961121",
          "detailUrl": "/details/Buaian-Kasih-1:1028:42961121"
        },
        {
          "eventId": "36210221",
          "title": "Berita Dunia",
          "programmeId": null,
          "episodeId": null,
          "datetime": "2021-02-03 23:00:00.0",
          "datetimeInUtc": "2021-02-03 15:00:00.0",
          "duration": "00:30:00",
          "siTrafficKey": "1:1028:42961122",
          "detailUrl": "/details/Berita-Dunia-1:1028:42961122"
        },
        {
          "eventId": "36210222",
          "title": "Atp Uncovered",
          "programmeId": null,
          "episodeId": null,
          "datetime": "2021-02-03 23:30:00.0",
          "datetimeInUtc": "2021-02-03 15:30:00.0",
          "duration": "00:30:00",
          "siTrafficKey": "1:1028:42961123",
          "detailUrl": "/details/Atp-Uncovered-1:1028:42961123"
        }
      ]
    }
  }
}
